parametrization_clean/__init__.py
parametrization_clean/app.py
parametrization_clean/cli.py
parametrization_clean/domain/__init__.py
parametrization_clean/domain/individual.py
parametrization_clean/domain/root_individual.py
parametrization_clean/domain/adaptation/__init__.py
parametrization_clean/domain/adaptation/factory.py
parametrization_clean/domain/adaptation/srinivas.py
parametrization_clean/domain/adaptation/strategy.py
parametrization_clean/domain/adaptation/xiao.py
parametrization_clean/domain/cost/__init__.py
parametrization_clean/domain/cost/factory.py
parametrization_clean/domain/cost/reax_error.py
parametrization_clean/domain/cost/strategy.py
parametrization_clean/domain/crossover/__init__.py
parametrization_clean/domain/crossover/double_pareto.py
parametrization_clean/domain/crossover/factory.py
parametrization_clean/domain/crossover/single_point.py
parametrization_clean/domain/crossover/strategy.py
parametrization_clean/domain/crossover/two_point.py
parametrization_clean/domain/crossover/uniform.py
parametrization_clean/domain/mutation/__init__.py
parametrization_clean/domain/mutation/central_uniform.py
parametrization_clean/domain/mutation/factory.py
parametrization_clean/domain/mutation/gauss.py
parametrization_clean/domain/mutation/nakata.py
parametrization_clean/domain/mutation/polynomial.py
parametrization_clean/domain/mutation/strategy.py
parametrization_clean/domain/neural_network/__init__.py
parametrization_clean/domain/neural_network/ann.py
parametrization_clean/domain/neural_network/extract_data.py
parametrization_clean/domain/neural_network/transform_data.py
parametrization_clean/domain/selection/__init__.py
parametrization_clean/domain/selection/factory.py
parametrization_clean/domain/selection/strategy.py
parametrization_clean/domain/selection/tournament.py
parametrization_clean/domain/utils/__init__.py
parametrization_clean/domain/utils/helpers.py
parametrization_clean/infrastructure/__init__.py
parametrization_clean_cdaksha-1.0.2.2.dist-info/LICENSE.md
parametrization_clean_cdaksha-1.0.2.2.dist-info/METADATA
parametrization_clean_cdaksha-1.0.2.2.dist-info/WHEEL
parametrization_clean_cdaksha-1.0.2.2.dist-info/entry_points.txt
parametrization_clean_cdaksha-1.0.2.2.dist-info/top_level.txt
parametrization_clean_cdaksha-1.0.2.2.dist-info/RECORD
