Metadata-Version: 2.1
Name: parametrization-clean-cdaksha
Version: 1.0.2.2
Summary: ReaxFF parameter optimization scheme using generational genetic algorithm and neural networks.
Home-page: https://github.com/cdaksha/parametrization_clean
Author: Chad Daksha
Author-email: daksha@udel.edu
License: MIT license
Keywords: parametrization_clean
Platform: UNKNOWN
Classifier: Development Status :: 2 - Pre-Alpha
Classifier: Intended Audience :: Developers
Classifier: License :: OSI Approved :: MIT License
Classifier: Natural Language :: English
Classifier: Programming Language :: Python :: 3
Requires-Python: >=3.6
Requires-Dist: numpy
Requires-Dist: pandas
Requires-Dist: Click
